odoo9_addon_partner_identification-9.0.1.0.0.99.dev52-py3.8-nspkg.pth
odoo_addons/partner_identification/README.rst
odoo_addons/partner_identification/__init__.py
odoo_addons/partner_identification/__openerp__.py
odoo_addons/partner_identification/i18n/am.po
odoo_addons/partner_identification/i18n/ar.po
odoo_addons/partner_identification/i18n/bg.po
odoo_addons/partner_identification/i18n/bs.po
odoo_addons/partner_identification/i18n/ca.po
odoo_addons/partner_identification/i18n/ca_ES.po
odoo_addons/partner_identification/i18n/cs.po
odoo_addons/partner_identification/i18n/da.po
odoo_addons/partner_identification/i18n/de.po
odoo_addons/partner_identification/i18n/el_GR.po
odoo_addons/partner_identification/i18n/en_GB.po
odoo_addons/partner_identification/i18n/es.po
odoo_addons/partner_identification/i18n/es_AR.po
odoo_addons/partner_identification/i18n/es_CO.po
odoo_addons/partner_identification/i18n/es_CR.po
odoo_addons/partner_identification/i18n/es_EC.po
odoo_addons/partner_identification/i18n/es_ES.po
odoo_addons/partner_identification/i18n/es_MX.po
odoo_addons/partner_identification/i18n/es_PE.po
odoo_addons/partner_identification/i18n/es_VE.po
odoo_addons/partner_identification/i18n/et.po
odoo_addons/partner_identification/i18n/eu.po
odoo_addons/partner_identification/i18n/fa.po
odoo_addons/partner_identification/i18n/fi.po
odoo_addons/partner_identification/i18n/fr.po
odoo_addons/partner_identification/i18n/fr_CH.po
odoo_addons/partner_identification/i18n/gl.po
odoo_addons/partner_identification/i18n/gl_ES.po
odoo_addons/partner_identification/i18n/he.po
odoo_addons/partner_identification/i18n/hr.po
odoo_addons/partner_identification/i18n/hr_HR.po
odoo_addons/partner_identification/i18n/hu.po
odoo_addons/partner_identification/i18n/id.po
odoo_addons/partner_identification/i18n/it.po
odoo_addons/partner_identification/i18n/ja.po
odoo_addons/partner_identification/i18n/ko.po
odoo_addons/partner_identification/i18n/lt.po
odoo9_addon_partner_identification-9.0.1.0.0.99.dev52.dist-info/METADATA
odoo9_addon_partner_identification-9.0.1.0.0.99.dev52.dist-info/WHEEL
odoo9_addon_partner_identification-9.0.1.0.0.99.dev52.dist-info/namespace_packages.txt
odoo9_addon_partner_identification-9.0.1.0.0.99.dev52.dist-info/top_level.txt
odoo9_addon_partner_identification-9.0.1.0.0.99.dev52.dist-info/RECORD
